Metadata-Version: 2.1
Name: STGMVA
Version: 1.0.0
Summary: Clustering, imputation, and integration for spatial transcriptomics using spatiotemporal gaussian mixture variational autoencoder
Home-page: https://github.com/narutoten520/STGMVA
Author: Teng Liu
Author-email: tengliu17@gmail.com
License: MIT
License-File: LICENSE
